ADBLibrary/__init__.py
ADBLibrary/adb_library.py
core/__init__.py
core/adb_connection.py
core/adb_interface.py
core/adb_proxy.py
robotframework_adblibrary-0.1.3.dist-info/licenses/LICENSE.txt
robotframework_adblibrary-0.1.3.dist-info/METADATA
robotframework_adblibrary-0.1.3.dist-info/WHEEL
robotframework_adblibrary-0.1.3.dist-info/top_level.txt
robotframework_adblibrary-0.1.3.dist-info/RECORD
