Metadata-Version: 2.4
Name: robotframework-adblibrary
Version: 0.1.3
Summary: Robot Framework library for Android ADB interaction
Home-page: https://github.com/ganesanluna/ADBLibrary
Author: Ganesan Selvaraj
Author-email: ganesanluna@yahoo.in
Project-URL: Documentation, https://github.com/ganesanluna/ADBLibrary#readme
Project-URL: Source, https://github.com/ganesanluna/ADBLibrary
Project-URL: Tracker, https://github.com/ganesanluna/ADBLibrary/issues
Keywords: robotframework,adb,android,automation,testing
Classifier: Programming Language :: Python :: 3
Classifier: Framework :: Robot Framework
Classifier: Framework :: Robot Framework :: Library
Classifier: License :: OSI Approved :: MIT License
Classifier: Operating System :: OS Independent
Requires-Python: >=3.10
License-File: LICENSE.txt
Requires-Dist: robotframework>=7.0
Requires-Dist: ipaddress>=1.0.23
Dynamic: author
Dynamic: author-email
Dynamic: classifier
Dynamic: description
Dynamic: description-content-type
Dynamic: home-page
Dynamic: keywords
Dynamic: license-file
Dynamic: project-url
Dynamic: requires-dist
Dynamic: requires-python
Dynamic: summary
